aiida_qe_app/__init__.py
aiida_qe_app/cli.py
aiida_qe_app/utils.py
aiida_qe_app/backend/__init__.py
aiida_qe_app/backend/main.py
aiida_qe_app/backend/app/__init__.py
aiida_qe_app/backend/app/api.py
aiida_qe_app/backend/app/calculation.py
aiida_qe_app/backend/app/code.py
aiida_qe_app/backend/app/computer.py
aiida_qe_app/backend/app/daemon.py
aiida_qe_app/backend/app/datanode.py
aiida_qe_app/backend/app/job_history.py
aiida_qe_app/backend/app/models.py
aiida_qe_app/backend/app/submit.py
aiida_qe_app/backend/app/utils.py
aiida_qe_app/backend/app/plugins/__init__.py
aiida_qe_app/backend/app/plugins/electronic_structure/__init__.py
aiida_qe_app/backend/app/plugins/electronic_structure/api.py
aiida_qe_app/backend/app/plugins/electronic_structure/utils.py
aiida_qe_app/backend/app/plugins/pdos/__init__.py
aiida_qe_app/backend/app/plugins/pdos/api.py
aiida_qe_app/backend/app/plugins/pdos/settings.py
aiida_qe_app/static/asset-manifest.json
aiida_qe_app/static/favicon.ico
aiida_qe_app/static/index.html
aiida_qe_app/static/manifest.json
aiida_qe_app/static/react-jsx-runtime-shim.js
aiida_qe_app/static/react-shim.js
aiida_qe_app/static/robots.txt
aiida_qe_app/static/example_structures/Au.cif
aiida_qe_app/static/example_structures/Co.cif
aiida_qe_app/static/example_structures/Diamond.cif
aiida_qe_app/static/example_structures/ETFA.xyz
aiida_qe_app/static/example_structures/GaAs.cif
aiida_qe_app/static/example_structures/Si.cif
aiida_qe_app/static/example_structures/SiO2.cif
aiida_qe_app/static/images/logo.png
aiida_qe_app/static/static/css/main.18f9e35d.css
aiida_qe_app/static/static/css/main.18f9e35d.css.map
aiida_qe_app/static/static/js/main.f1394b82.js
aiida_qe_app/static/static/js/main.f1394b82.js.LICENSE.txt
aiida_qe_app/static/static/js/main.f1394b82.js.map
aiida_qe_app/workflows/__init__.py
aiida_qe_app/workflows/qeapp_workchain.py
aiida_qe_app/workflows/qeapp_workgraph.py
aiida_qe_app-0.0.3.dist-info/licenses/LICENSE
aiida_qe_app-0.0.3.dist-info/METADATA
aiida_qe_app-0.0.3.dist-info/WHEEL
aiida_qe_app-0.0.3.dist-info/entry_points.txt
aiida_qe_app-0.0.3.dist-info/top_level.txt
aiida_qe_app-0.0.3.dist-info/RECORD
