Metadata-Version: 2.4
Name: aiida-qe-app
Version: 0.0.3
Summary: Design flexible node-based workflow for AiiDA calculation.
Author-email: Xing Wang <xingwang1991@gmail.com>
License: MIT License
Project-URL: Documentation, https://aiida-qe-app.readthedocs.io
Project-URL: Source, https://github.com/superstar54/aiida-qe-app
Keywords: aiida,workflows
Classifier: Development Status :: 1 - Planning
Classifier: Framework :: AiiDA
Classifier: License :: OSI Approved :: MIT License
Classifier: Operating System :: POSIX :: Linux
Classifier: Operating System :: MacOS :: MacOS X
Classifier: Programming Language :: Python
Classifier: Programming Language :: Python :: 3.9
Classifier: Programming Language :: Python :: 3.10
Classifier: Programming Language :: Python :: 3.11
Classifier: Programming Language :: Python :: 3.12
Classifier: Topic :: Scientific/Engineering
Requires-Python: >=3.9
License-File: LICENSE
Requires-Dist: ase
Requires-Dist: aiida-core>=2.6
Requires-Dist: aiida-gui-apps
Provides-Extra: docs
Requires-Dist: sphinx_rtd_theme; extra == "docs"
Requires-Dist: sphinx~=7.2; extra == "docs"
Requires-Dist: sphinx-copybutton~=0.5.0; extra == "docs"
Requires-Dist: sphinx-design~=0.5.0; extra == "docs"
Requires-Dist: sphinx-notfound-page~=1.0; extra == "docs"
Requires-Dist: sphinxext-rediraffe~=0.2.4; extra == "docs"
Requires-Dist: sphinx-intl~=2.1.0; extra == "docs"
Requires-Dist: sphinx-gallery; extra == "docs"
Requires-Dist: myst-nb~=1.0.0; extra == "docs"
Requires-Dist: nbsphinx; extra == "docs"
Provides-Extra: pre-commit
Requires-Dist: pre-commit~=2.2; extra == "pre-commit"
Requires-Dist: pylint~=2.17.4; extra == "pre-commit"
Dynamic: license-file
